nnthvn/__init__.py
nnthvn/module1.py
nnthvn/module12.py
nnthvn/module2.py
nnthvn/tttttt.py
nnthvn/456/__init__.py
nnthvn/nnthvn/__init__.py
nnthvn/nnthvn/module1.py
nnthvn/nnthvn/module2.py
nnthvn/tests/__init__.py
nnthvn/tests/test_module1.py
nnthvn/tests/test_module2.py
nnthvn/tests/test_module1/__init__.py
nnthvn-0.8.0.dist-info/METADATA
nnthvn-0.8.0.dist-info/WHEEL
nnthvn-0.8.0.dist-info/top_level.txt
nnthvn-0.8.0.dist-info/RECORD
